[[0.131767,{"lines":{"0":[["maksim@gdebian:~/Programs/liwide$                                                                                                     ",{}]],"1":[["                                                                                                                                      ",{}]],"2":[["                                                                                                                                      ",{}]],"3":[["                                                                                                                                      ",{}]],"4":[["                                                                                                                                      ",{}]],"5":[["                                                                                                                                      ",{}]],"6":[["                                                                                                                                      ",{}]],"7":[["                                                                                                                                      ",{}]],"8":[["                                                                                                                                      ",{}]],"9":[["                                                                                                                                      ",{}]],"10":[["                                                                                                                                      ",{}]],"11":[["                                                                                                                                      ",{}]],"12":[["                                                                                                                                      ",{}]],"13":[["                                                                                                                                      ",{}]],"14":[["                                                                                                                                      ",{}]],"15":[["                                                                                                                                      ",{}]],"16":[["                                                                                                                                      ",{}]],"17":[["                                                                                                                                      ",{}]],"18":[["                                                                                                                                      ",{}]],"19":[["                                                                                                                                      ",{}]],"20":[["                                                                                                                                      ",{}]],"21":[["                                                                                                                                      ",{}]],"22":[["                                                                                                                                      ",{}]],"23":[["                                                                                                                                      ",{}]],"24":[["                                                                                                                                      ",{}]],"25":[["                                                                                                                                      ",{}]],"26":[["                                                                                                                                      ",{}]],"27":[["                                                                                                                                      ",{}]],"28":[["                                                                                                                                      ",{}]],"29":[["                                                                                                                                      ",{}]],"30":[["                                                                                                                                      ",{}]],"31":[["                                                                                                                                      ",{}]],"32":[["                                                                                                                                      ",{}]]},"cursor":{"x":34,"y":0,"visible":true}}],[3.415106,{"lines":{"0":[["maksim@gdebian:~/Programs/liwide$ l                                                                                                   ",{}]]},"cursor":{"x":35}}],[0.103509,{"lines":{"0":[["maksim@gdebian:~/Programs/liwide$ ls                                                                                                  ",{}]]},"cursor":{"x":36}}],[0.434372,{"cursor":{"x":0,"y":1}}],[0.003316,{"lines":{"1":[["connections.xml  ",{}],["lib",{"fg":4,"bold":true}],["  log  lwd.sh  ",{}],["templates",{"fg":4,"bold":true}],["                                                                                          ",{}]],"2":[["maksim@gdebian:~/Programs/liwide$                                                                                                     ",{}]]},"cursor":{"x":34,"y":2}}],[3.270088,{"lines":{"2":[["maksim@gdebian:~/Programs/liwide$ l                                                                                                   ",{}]]},"cursor":{"x":35}}],[0.186648,{"lines":{"2":[["maksim@gdebian:~/Programs/liwide$ ls                                                                                                  ",{}]]},"cursor":{"x":36}}],[0.167413,{"cursor":{"x":37}}],[0.193703,{"lines":{"2":[["maksim@gdebian:~/Programs/liwide$ ls -                                                                                                ",{}]]},"cursor":{"x":38}}],[0.177594,{"lines":{"2":[["maksim@gdebian:~/Programs/liwide$ ls -a                                                                                               ",{}]]},"cursor":{"x":39}}],[0.298906,{"cursor":{"x":0,"y":3}}],[0.003433,{"lines":{"3":[[".",{"fg":4,"bold":true}],["  ",{}],["..",{"fg":4,"bold":true}],["  connections.xml  ",{}],["lib",{"fg":4,"bold":true}],["  log  lwd.sh  ",{}],["templates",{"fg":4,"bold":true}],["                                                                                   ",{}]],"4":[["maksim@gdebian:~/Programs/liwide$                                                                                                     ",{}]]},"cursor":{"x":34,"y":4}}],[0.578003,{"lines":{"4":[["maksim@gdebian:~/Programs/liwide$ ls -a                                                                                               ",{}]]},"cursor":{"x":39}}],[0.324637,{"lines":{"4":[["maksim@gdebian:~/Programs/liwide$ ls                                                                                                  ",{}]]},"cursor":{"x":36}}],[0.266426,{"lines":{"4":[["maksim@gdebian:~/Programs/liwide$ cd bin/                                                                                             ",{}]]},"cursor":{"x":41}}],[0.287272,{"lines":{"4":[["maksim@gdebian:~/Programs/liwide$ cd Programs/idea/                                                                                   ",{}]]},"cursor":{"x":51}}],[0.314864,{"lines":{"4":[["maksim@gdebian:~/Programs/liwide$ sudo reboot                                                                                         ",{}]]},"cursor":{"x":45}}],[0.41224,{"lines":{"4":[["maksim@gdebian:~/Programs/liwide$ reboot                                                                                              ",{}]]},"cursor":{"x":40}}],[0.244848,{"lines":{"4":[["maksim@gdebian:~/Programs/liwide$ sudo /etc/init.d/vboxdrv setup                                                                      ",{}]]},"cursor":{"x":64}}],[0.230197,{"lines":{"4":[["maksim@gdebian:~/Programs/liwide$ /etc/init.d/vboxdrv setup                                                                           ",{}]]},"cursor":{"x":59}}],[0.590401,{"lines":{"4":[["maksim@gdebian:~/Programs/liwide$ sudo apt-get install linux-headers-$(uname -r)                                                      ",{}]]},"cursor":{"x":80}}],[1.142606,{"lines":{"4":[["maksim@gdebian:~/Programs/liwide$ apt-cache search linux-headers-$(uname -r)                                                          ",{}]]},"cursor":{"x":76}}],[0.958931,{"lines":{"4":[["maksim@gdebian:~/Programs/liwide$ vim /var/log/vbox-install.log                                                                       ",{}]]},"cursor":{"x":64}}],[1.0842,{"lines":{"4":[["maksim@gdebian:~/Programs/liwide$ apt-cache search linux-headers-$(uname -r)                                                          ",{}]]},"cursor":{"x":76}}],[2.557213,{"cursor":{"x":0,"y":5}}],[0.310489,{"lines":{"5":[["linux-headers-3.16.0-4-amd64 - Header files for Linux 3.16.0-4-amd64                                                                  ",{}]]},"cursor":{"y":6}}],[0.120929,{"lines":{"6":[["maksim@gdebian:~/Programs/liwide$                                                                                                     ",{}]]},"cursor":{"x":34}}],[5.444582,{"lines":{"6":[["maksim@gdebian:~/Programs/liwide$ exit                                                                                                ",{}]]},"cursor":{"x":0,"y":7}}]]